che/__init__.py
che/che.py
che-0.5.0.dist-info/METADATA
che-0.5.0.dist-info/WHEEL
che-0.5.0.dist-info/licenses/LICENSE
che-0.5.0.dist-info/RECORD
