Metadata-Version: 2.1
Name: che
Version: 0.5.0
Summary: Add your description here
Author-email: atu4403 <73111778+atu4403@users.noreply.github.com>
License-File: LICENSE
Requires-Python: >=3.8
